zec2/__init__.py
zec2/aws_ec2.py
zec2/cli.py
zec2-0.5.0.dist-info/LICENSE
zec2-0.5.0.dist-info/METADATA
zec2-0.5.0.dist-info/WHEEL
zec2-0.5.0.dist-info/entry_points.txt
zec2-0.5.0.dist-info/top_level.txt
zec2-0.5.0.dist-info/RECORD
