Metadata-Version: 2.1
Name: zec2
Version: 0.5.0
Summary: Easily ssh to your AWS EC2 instances
Home-page: https://github.com/arrrlo/zec2
Author: Ivan Arar
Author-email: ivan.arar@gmail.com
License: MIT
Project-URL: Source, https://github.com/arrrlo/zec2
Keywords: amazon,aws,ec2,ssh,instance
Classifier: Development Status :: 4 - Beta
Classifier: Intended Audience :: Developers
Classifier: Topic :: Software Development :: Build Tools
Classifier: License :: OSI Approved :: MIT License
Classifier: Programming Language :: Python :: 3.6
Classifier: Programming Language :: Python :: 3.7
Classifier: Programming Language :: Python :: 3.8
Classifier: Programming Language :: Python :: 3.9
License-File: LICENSE
Requires-Dist: click (>=7.0)
Requires-Dist: six (>=1.14.0)
Requires-Dist: boto3 (>=1.7.69)
Requires-Dist: terminaltables (~=3.1.0)
